LICENSE.txt
MANIFEST.in
README.markdown
setup.py
examples/evil_ssl_client.py
examples/mail_relay.py
examples/server.crt
examples/server.key
examples/ssl_client.py
examples/ssl_server.py
examples/benchmarking/benchmark.eml
examples/benchmarking/client.py
examples/benchmarking/server.py
secure_smtpd/__init__.py
secure_smtpd/fake_credential_validator.py
secure_smtpd/process_pool.py
secure_smtpd/proxy_server.py
secure_smtpd/smtp_channel.py
secure_smtpd/smtp_server.py
secure_smtpd/store_credentials.py
secure_smtpd.egg-info/PKG-INFO
secure_smtpd.egg-info/SOURCES.txt
secure_smtpd.egg-info/dependency_links.txt
secure_smtpd.egg-info/not-zip-safe
secure_smtpd.egg-info/requires.txt
secure_smtpd.egg-info/top_level.txt
secure_smtpd/config/__init__.py
secure_smtpd/config/log.py