Metadata-Version: 1.1
Name: secure-smtpd
Version: 3.0.0
Summary: Adds support for SSL, AUTH, and other goodies, to Petri Lehtinen's SMTPD library.
Home-page: https://github.com/bcoe/secure-smtpd
Author: Benjamin Coe
Author-email: bencoe@gmail.com
License: ISC
Keywords: secure ssl auth smtp smtpd server
Platform: UNKNOWN
Classifier: Development Status :: 4 - Beta
Classifier: Topic :: Communications :: Email :: Mail Transport Agents
Classifier: Programming Language :: Python :: 2
Classifier: Programming Language :: Python :: 2.7
Classifier: Programming Language :: Python :: 3
Classifier: Programming Language :: Python :: 3.2
Classifier: License :: OSI Approved :: ISC License (ISCL)
